{
  "kind": "coverage_report",
  "version": "1.0",
  "generatedAt": "2026-02-06T12:57:07.752Z",
  "sources": {
    "buildRequest": true,
    "implementationPlan": true
  },
  "requirements": {
    "total": 1,
    "implemented": 1,
    "items": [
      {
        "id": "REQ-27",
        "summary": "Fix the runtime error on initial load (Landing/Home route) where `useManualAuth` is called outside of `ManualAuthProvider` by wrapping the application route tree with `<ManualAuthProvider>` at a level that covers `RootLayout`, `AppLayout`, `AppHeader`, and all routed pages, without editing `frontend/src/main.tsx` (immutable).",
        "status": "implemented",
        "plannedFiles": [
          "frontend/src/App.tsx"
        ],
        "matchedFiles": [
          "frontend/src/App.tsx"
        ]
      }
    ]
  },
  "changedFiles": [
    "build-request.json",
    "feature_evidence.json",
    "frontend-file-summaries.txt",
    "frontend-implementation-plan.json",
    "frontend/src/App.tsx",
    "project_state.json",
    "scratch/component-selection.json",
    "spec.md",
    "spec_vs_diff_report.json"
  ]
}